{
  "items": [
    { "id": "broccoli_list_cheddar_potato", "name": "Broccoli and Cheddar Potato", "cost": 3.49 },
    { "id": "bacon_list_cheddar_potato", "name": "Bacon and Cheddar Potato", "cost": 3.49 },
    { "id": "chili_list_cheese_potato", "name": "Chili and Cheese Potato", "cost": 3.49 },
    { "id": "breakfast_baconator", "name": "Breakfast Baconator", "cost": 4.59 },
    { "id": "breakfast_baconator", "name": "Breakfast Baconator", "combo": true, "cost": 5.99 },
    { "id": "french_toast_sandwich", "name": "French Toast Sandwich", "cost": 4.29 },
    { "id": "french_toast_sandwich", "name": "French Toast Sandwich", "combo": true, "cost": 5.69 },
    { "id": "egg_muffin", "name": "Egg Muffin", "cost": 3.39 },
    { "id": "egg_muffin", "name": "Egg Muffin", "combo": true, "cost": 4.99 },
    { "id": "chicken_on_french_toast", "name": "Chicken on French Toast", "cost": 3.09 },
    { "id": "chicken_on_french_toast", "name": "Chicken on French Toast", "combo": true, "cost": 4.59 },
    { "id": "pancake_platter", "name": "Pancake Platter", "cost": 6.19 },
    { "id": "double_sausage_muffin", "name": "Double Sausage Muffin", "cost": 3.29 },
    { "id": "double_sausage_muffin", "name": "Double Sausage Muffin", "combo": true, "cost": 4.89 },
    { "id": "pancake", "name": "Pancakes", "cost": 2.89 },
    { "id": "french_toast", "name": "French Toast", "cost": 2.89 },
    { "id": "oatmeal", "name": "Oatmeal", "cost": 2.49 },
    { "id": "junior_bacon_cheeseburger", "name": "Junior Bacon Cheeseburger", "cost": 4.99 },
    { "id": "chicken_go_wrap", "name": "Chicken Go Wrap", "cost": 4.99 },
    { "id": "junior_crispy_chicken_club", "name": "Junior Crispy Chicken Club", "cost": 4.99 },
    { "id": "single", "base": "single", "name": "Single Hamburger", "cost": 4.59 },
    { "id": "single_combo", "base": "single", "name": "Single Combo", "cost": { "small": 6.79, "medium": 9.18, "large": 9.48 }, "combo": true },
    { "id": "double", "base": "double", "name": "Double Hamburger", "cost": 5.99 },
    { "id": "double_combo", "base": "double", "name": "Double Combo", "cost": { "small": 8.09, "medium": 8.98, "large": 9.28 }, "combo": true },
    { "id": "triple", "base": "triple", "name": "Triple Hamburger", "cost": 6.99 },
    { "id": "triple_combo", "base": "triple", "name": "Triple Combo", "cost": { "small": 8.99, "medium": 8.98, "large": 9.28 }, "combo": true },
    { "id": "baconator", "base": "baconator", "name": "Baconator Hamburger", "cost": 6.99 },
    { "id": "baconator_combo", "base": "baconator", "name": "Baconator Combo", "cost": { "small": 8.89, "medium": 8.88, "large": 9.18 }, "combo": true },
    { "id": "bacon_deluxe", "base": "bacon deluxe", "name": "Bacon Deluxe Hamburger", "cost": 5.89 },
    { "id": "bacon_deluxe_combo", "base": "bacon deluxe", "name": "Bacon Deluxe Combo", "cost": { "small": 7.79, "medium": 8.18, "large": 8.48 }, "combo": true },
    { "id": "spicy", "base": "spicy", "name": "Spicy Chikenburger", "cost": 5.99 },
    { "id": "spicy_combo", "base": "spicy", "name": "Spicy Combo", "cost": { "small": 8.19, "medium": 9.18, "large": 9.38 }, "combo": true },
    { "id": "homestyle", "base": "homestyle", "name": "Homestyle Chickburger", "cost": 5.99 },
    { "id": "homestyle_combo", "base": "homestyle", "name": "Homestyle Chickenburger", "cost": { "small": 8.19, "medium": 9.18, "large": 9.38 }, "combo": true },
    { "id": "asiago_range_chicken_club", "base": "asiago range chicken club", "name": "Asiago Range Chicken Club", "cost": 6.89 },
    { "id": "asiago_range_chicken_club_combo", "base": "asiago range chicken club", "name": "Asiago Range Chicken Club", "cost": { "small": 8.89, "medium": 8.88, "large": 9.18 }, "combo": true },
    { "id": "ultimate_chicken_grill", "base": "ultimate chicken grill", "name": "Ultimate Chicken Grill", "cost": 5.99 },
    { "id": "ultimate_chicken_grill_combo", "base": "ultimate chicken grill", "name": "Ultimate Chicken Grill Combo", "cost": { "small": 8.19, "medium": 9.18, "large": 9.38 }, "combo": true },
    { "id": "10_piece_nuggets", "base": "10 piece nuggets", "name": "10 Piece Nuggets", "cost": 5.49 },
    { "id": "10_piece_nuggets_combo", "base": "10 piece nuggets", "name": "10 Piece Nuggets Combo", "cost": { "small": 7.29, "medium": 8.18, "large": 8.58 }, "combo": true },
    { "id": "premium_cod", "base": "premium cod", "name": "Premium Cod", "cost": 5.49 },
    { "id": "premium_cod_combo", "base": "premium cod", "name": "Premium Cod Combo", "cost": { "small": 7.49, "medium": 8.38, "large": 8.88 }, "combo": true },
    { "id": "strawberry_smoothie", "base": "strawberry smoothie", "name": "Strawberry Smoothie", "cost": { "small": 2.99, "large": 3.79 }, "combo": false },
    { "id": "guava_smoothie", "base": "guava smoothie", "name": "Guava Smoothie", "cost": { "small": 2.99, "large": 3.79 }, "combo": false },
    { "id": "mango_passion_smoothie", "base": "mango passion smoothie", "name": "Mango Passion Smoothie", "cost": { "small": 2.99, "large": 3.79 }, "combo": false },
    { "id": "wild_berry_smoothie", "base": "wild berry smoothie", "name": "Wild Berry Smoothie", "cost": { "small": 2.99, "large": 3.79 }, "combo": false },
    { "id": "strawberry_banana_smoothie", "base": "strawberry banana smoothie", "name": "Strawberry Banana Smoothie", "cost": { "small": 2.99, "large": 3.79 }, "combo": false },
    { "id": "french_fry", "base": "french fries", "name": "French Fries", "combo": false, "cost": { "small": 1.59, "medium": 1.79, "large": 2.29 } },
    { "id": "waffle_fry", "base": "waffle fries", "name": "Waffle Fries", "combo": false, "cost": { "small": 2.18, "medium": 2.28, "large": 2.78 } },
    { "id": "coca_cola", "base": "coca cola", "name": "Coca Cola", "combo": false, "cost": { "small": 2.09, "medium": 2.59, "large": 2.89 } },
    { "id": "diet_coke", "base": "diet coke", "name": "Diet Coke", "combo": false, "cost": { "small": 2.09, "medium": 2.59, "large": 2.89 } },
    { "id": "barq", "base": "barq", "name": "Barqs", "combo": false, "cost": { "small": 2.09, "medium": 2.59, "large": 2.89 } },
    { "id": "fanta", "base": "fanta", "name": "Fanta", "combo": false, "cost": { "small": 2.09, "medium": 2.59, "large": 2.89 } },
    { "id": "sprite", "base": "sprite", "name": "Sprite", "combo": false, "cost": { "small": 2.09, "medium": 2.59, "large": 2.89 } },
    { "id": "iced_tea", "base": "iced tea", "name": "Iced Tea", "combo": false, "cost": { "small": 2.09, "medium": 2.59, "large": 2.89 } },
    { "id": "sweet_black_coffee", "base": "sweet black coffee", "name": "Sweet Black Coffee", "combo": false, "cost": { "small": 2.09, "medium": 2.59, "large": 2.89 } },
    { "id": "french_vanilla_coffee", "base": "french vanilla coffee", "name": "French Vanilla Coffee", "combo": false, "cost": { "small": 2.09, "medium": 2.59, "large": 2.89 } },
    { "id": "cappuccino_coffee", "base": "cappuccino coffee", "name": "Cappuccino Coffee", "combo": false, "cost": { "small": 2.09, "medium": 2.59, "large": 2.89 } },
    { "id": "mocha_shake", "base": "mocka shake", "name": "Mocha Shake", "combo": false, "cost": { "small": 2.09, "medium": 2.59, "large": 2.89 } },
    { "id": "caramel_shake", "base": "caramel shake", "name": "Caramel Shake", "combo": false, "cost": { "small": 2.09, "medium": 2.59, "large": 2.89 } },
    { "id": "lemonade", "base": "lemonade", "name": "Lemonade", "combo": false, "cost": { "small": 2.09, "medium": 2.59, "large": 2.89 } },
    { "id": "strawberry_lemonade", "base": "strawberry lemonade", "name": "Strawberry Lemonade", "combo": false, "cost": { "small": 2.09, "medium": 2.59, "large": 2.89 } },
    { "id": "wild_berry_lemonade", "base": "wild berry lemonade", "name": "Wild Berry Lemonade", "combo": false, "cost": { "small": 2.09, "medium": 2.59, "large": 2.89 } },
    { "id": "loaded_fry", "base": "loaded fries", "name": "Loaded Fries", "combo": false, "cost": 2.39 },
    { "id": "chili_fry", "base": "chili fries", "name": "Chili Fries", "combo": false, "cost": 2.39 },
    { "id": "garden_salad", "base": "garden salad", "name": "Garden Salad", "combo": false, "cost": 2.49 },
    { "id": "caesar_salad", "base": "caesar salad", "name": "Caesar Salad", "combo": false, "cost": 2.49 },
    { "id": "chili", "base": "chili", "name": "Chili", "combo": false, "cost": { "small": 2.69, "large": 3.09 } },
    { "id": "cheese_potato", "base": "cheese potato", "name": "Cheese Potato", "combo": false, "cost": 3.39 },
    { "id": "vanilla_shake", "base": "vanilla shake", "name": "Vanilla Shake", "combo": false, "cost": { "small": 2.99, "large": 3.79 } },
    { "id": "mango_passion_shake", "base": "mango passion shake", "name": "Mango Passion Shake", "combo": false, "cost": { "small": 2.99, "large": 3.79 } },
    { "id": "strawberry_shake", "base": "strawberry shake", "name": "Strawberry Shake", "combo": false, "cost": { "small": 2.99, "large": 3.79 } },
    { "id": "guava_shake", "base": "guava shake", "name": "Guava Shake", "combo": false, "cost": { "small": 2.99, "large": 3.79 } },
    { "id": "chocolate_shake", "base": "chocolate shake", "name": "Chocolate Shake", "combo": false, "cost": { "small": 2.99, "large": 3.79 } },
    { "id": "banana_shake", "base": "banana shake", "name": "Banana Shake", "combo": false, "cost": { "small": 2.99, "large": 3.79 } },
    { "id": "wild_berry_shake", "base": "wild berry shake", "name": "Wild Berry Shake", "combo": false, "cost": { "small": 2.99, "large": 3.79 } },
    { "id": "vanilla_frosty", "base": "vanilla frosty", "name": "Vanilla Frosty", "combo": false, "cost": { "small": 1.99, "large": 2.69 } },
    { "id": "chocolate_frosty", "base": "chocolate frosty", "name": "Chocolate Frosty", "combo": false, "cost": { "small": 1.99, "large": 2.69 } },
    { "id": "apple_pie", "base": "apple_pie", "name": "Apple Pie", "combo": false, "cost": 1.79 },
    { "id": "apple_pecan_salad", "base": "apple pecan salad", "name": "Apple Pecan Salad", "combo": false, "cost": { "half": 6.49, "full": 8.69 } },
    { "id": "spicy_caesar_salad", "base": "spicy caesar salad", "name": "Spicy Caesar Salad", "combo": false, "cost": { "half": 6.49, "full": 8.69 } },
    { "id": "taco_salad", "base": "taco salad", "name": "Taco Salad", "combo": false, "cost": { "half": 6.49, "full": 8.69 } },
    { "id": "southwest_avacado_salad", "base": "southwest avacado salad", "name": "Southwest Avacado Salad", "combo": false, "cost": { "half": 6.49, "full": 8.69 } }
  ],
  "combos": {
      "1": "single",
      "2": "double",
      "3": "triple",
      "4": "baconator",
      "5": "bacon deluxe",
      "6": "spicy",
      "7": "homestyle",
      "8": "asiago range chicken club",
      "9": "ultimate chicken grill",
      "10": "10 piece nuggets",
      "11": "premium cod"
  },
  "waffle_fry_extra_cost": 0.59
}
